xmlapply/__init__.py
xmlapply/apply.py
xmlapply/cli.py
xmlapply/config.py
xmlapply/parser.py
xmlapply/py.typed
xmlapply-0.1.0.dist-info/METADATA
xmlapply-0.1.0.dist-info/WHEEL
xmlapply-0.1.0.dist-info/entry_points.txt
xmlapply-0.1.0.dist-info/RECORD
