Metadata-Version: 2.3
Name: xmlapply
Version: 0.1.0
Summary: A tool for applying XML-defined file changes to a project directory
Project-URL: Repository, https://github.com/darinkishore/xmlapply
Author-email: Darin <86675935+darinkishore@users.noreply.github.com>
Classifier: Development Status :: 3 - Alpha
Classifier: Environment :: Console
Classifier: Intended Audience :: Developers
Classifier: Programming Language :: Python :: 3.11
Classifier: Topic :: Software Development :: Libraries :: Python Modules
Requires-Python: >=3.11
Requires-Dist: click>=8.1.7
Requires-Dist: pyperclip>=1.8.2
Requires-Dist: pyyaml>=6.0
